{"nodes": [{"id": "c_users_theco_downloads_edubreezy_web_edutemp_src_app_api_mobile_dashboard_parent_route_js", "label": "route.js", "file_type": "code", "source_file": "C:\\Users\\theco\\Downloads\\edubreezy_web\\edutemp\\src\\app\\api\\mobile\\dashboard\\parent\\route.js", "source_location": "L1"}, {"id": "route_get", "label": "GET()", "file_type": "code", "source_file": "C:\\Users\\theco\\Downloads\\edubreezy_web\\edutemp\\src\\app\\api\\mobile\\dashboard\\parent\\route.js", "source_location": "L9"}, {"id": "route_fetchchildren", "label": "fetchChildren()", "file_type": "code", "source_file": "C:\\Users\\theco\\Downloads\\edubreezy_web\\edutemp\\src\\app\\api\\mobile\\dashboard\\parent\\route.js", "source_location": "L81"}, {"id": "route_fetchnotices", "label": "fetchNotices()", "file_type": "code", "source_file": "C:\\Users\\theco\\Downloads\\edubreezy_web\\edutemp\\src\\app\\api\\mobile\\dashboard\\parent\\route.js", "source_location": "L122"}, {"id": "route_fetchupcomingevents", "label": "fetchUpcomingEvents()", "file_type": "code", "source_file": "C:\\Users\\theco\\Downloads\\edubreezy_web\\edutemp\\src\\app\\api\\mobile\\dashboard\\parent\\route.js", "source_location": "L163"}, {"id": "route_fetchactiveacademicyear", "label": "fetchActiveAcademicYear()", "file_type": "code", "source_file": "C:\\Users\\theco\\Downloads\\edubreezy_web\\edutemp\\src\\app\\api\\mobile\\dashboard\\parent\\route.js", "source_location": "L194"}, {"id": "route_fetchchildattendance", "label": "fetchChildAttendance()", "file_type": "code", "source_file": "C:\\Users\\theco\\Downloads\\edubreezy_web\\edutemp\\src\\app\\api\\mobile\\dashboard\\parent\\route.js", "source_location": "L206"}, {"id": "route_fetchchildhomework", "label": "fetchChildHomework()", "file_type": "code", "source_file": "C:\\Users\\theco\\Downloads\\edubreezy_web\\edutemp\\src\\app\\api\\mobile\\dashboard\\parent\\route.js", "source_location": "L290"}, {"id": "route_fetchchildexams", "label": "fetchChildExams()", "file_type": "code", "source_file": "C:\\Users\\theco\\Downloads\\edubreezy_web\\edutemp\\src\\app\\api\\mobile\\dashboard\\parent\\route.js", "source_location": "L340"}, {"id": "route_fetchchildfees", "label": "fetchChildFees()", "file_type": "code", "source_file": "C:\\Users\\theco\\Downloads\\edubreezy_web\\edutemp\\src\\app\\api\\mobile\\dashboard\\parent\\route.js", "source_location": "L406"}], "edges": [{"source": "c_users_theco_downloads_edubreezy_web_edutemp_src_app_api_mobile_dashboard_parent_route_js", "target": "server", "relation": "imports_from", "confidence": "EXTRACTED", "source_file": "C:\\Users\\theco\\Downloads\\edubreezy_web\\edutemp\\src\\app\\api\\mobile\\dashboard\\parent\\route.js", "source_location": "L1", "weight": 1.0}, {"source": "c_users_theco_downloads_edubreezy_web_edutemp_src_app_api_mobile_dashboard_parent_route_js", "target": "prisma", "relation": "imports_from", "confidence": "EXTRACTED", "source_file": "C:\\Users\\theco\\Downloads\\edubreezy_web\\edutemp\\src\\app\\api\\mobile\\dashboard\\parent\\route.js", "source_location": "L2", "weight": 1.0}, {"source": "c_users_theco_downloads_edubreezy_web_edutemp_src_app_api_mobile_dashboard_parent_route_js", "target": "route_get", "relation": "contains", "confidence": "EXTRACTED", "source_file": "C:\\Users\\theco\\Downloads\\edubreezy_web\\edutemp\\src\\app\\api\\mobile\\dashboard\\parent\\route.js", "source_location": "L9", "weight": 1.0}, {"source": "c_users_theco_downloads_edubreezy_web_edutemp_src_app_api_mobile_dashboard_parent_route_js", "target": "route_fetchchildren", "relation": "contains", "confidence": "EXTRACTED", "source_file": "C:\\Users\\theco\\Downloads\\edubreezy_web\\edutemp\\src\\app\\api\\mobile\\dashboard\\parent\\route.js", "source_location": "L81", "weight": 1.0}, {"source": "c_users_theco_downloads_edubreezy_web_edutemp_src_app_api_mobile_dashboard_parent_route_js", "target": "route_fetchnotices", "relation": "contains", "confidence": "EXTRACTED", "source_file": "C:\\Users\\theco\\Downloads\\edubreezy_web\\edutemp\\src\\app\\api\\mobile\\dashboard\\parent\\route.js", "source_location": "L122", "weight": 1.0}, {"source": "c_users_theco_downloads_edubreezy_web_edutemp_src_app_api_mobile_dashboard_parent_route_js", "target": "route_fetchupcomingevents", "relation": "contains", "confidence": "EXTRACTED", "source_file": "C:\\Users\\theco\\Downloads\\edubreezy_web\\edutemp\\src\\app\\api\\mobile\\dashboard\\parent\\route.js", "source_location": "L163", "weight": 1.0}, {"source": "c_users_theco_downloads_edubreezy_web_edutemp_src_app_api_mobile_dashboard_parent_route_js", "target": "route_fetchactiveacademicyear", "relation": "contains", "confidence": "EXTRACTED", "source_file": "C:\\Users\\theco\\Downloads\\edubreezy_web\\edutemp\\src\\app\\api\\mobile\\dashboard\\parent\\route.js", "source_location": "L194", "weight": 1.0}, {"source": "c_users_theco_downloads_edubreezy_web_edutemp_src_app_api_mobile_dashboard_parent_route_js", "target": "route_fetchchildattendance", "relation": "contains", "confidence": "EXTRACTED", "source_file": "C:\\Users\\theco\\Downloads\\edubreezy_web\\edutemp\\src\\app\\api\\mobile\\dashboard\\parent\\route.js", "source_location": "L206", "weight": 1.0}, {"source": "c_users_theco_downloads_edubreezy_web_edutemp_src_app_api_mobile_dashboard_parent_route_js", "target": "route_fetchchildhomework", "relation": "contains", "confidence": "EXTRACTED", "source_file": "C:\\Users\\theco\\Downloads\\edubreezy_web\\edutemp\\src\\app\\api\\mobile\\dashboard\\parent\\route.js", "source_location": "L290", "weight": 1.0}, {"source": "c_users_theco_downloads_edubreezy_web_edutemp_src_app_api_mobile_dashboard_parent_route_js", "target": "route_fetchchildexams", "relation": "contains", "confidence": "EXTRACTED", "source_file": "C:\\Users\\theco\\Downloads\\edubreezy_web\\edutemp\\src\\app\\api\\mobile\\dashboard\\parent\\route.js", "source_location": "L340", "weight": 1.0}, {"source": "c_users_theco_downloads_edubreezy_web_edutemp_src_app_api_mobile_dashboard_parent_route_js", "target": "route_fetchchildfees", "relation": "contains", "confidence": "EXTRACTED", "source_file": "C:\\Users\\theco\\Downloads\\edubreezy_web\\edutemp\\src\\app\\api\\mobile\\dashboard\\parent\\route.js", "source_location": "L406", "weight": 1.0}, {"source": "route_get", "target": "route_fetchchildren", "relation": "calls", "confidence": "EXTRACTED", "source_file": "C:\\Users\\theco\\Downloads\\edubreezy_web\\edutemp\\src\\app\\api\\mobile\\dashboard\\parent\\route.js", "source_location": "L35", "weight": 1.0}, {"source": "route_get", "target": "route_fetchnotices", "relation": "calls", "confidence": "EXTRACTED", "source_file": "C:\\Users\\theco\\Downloads\\edubreezy_web\\edutemp\\src\\app\\api\\mobile\\dashboard\\parent\\route.js", "source_location": "L36", "weight": 1.0}, {"source": "route_get", "target": "route_fetchupcomingevents", "relation": "calls", "confidence": "EXTRACTED", "source_file": "C:\\Users\\theco\\Downloads\\edubreezy_web\\edutemp\\src\\app\\api\\mobile\\dashboard\\parent\\route.js", "source_location": "L37", "weight": 1.0}, {"source": "route_get", "target": "route_fetchactiveacademicyear", "relation": "calls", "confidence": "EXTRACTED", "source_file": "C:\\Users\\theco\\Downloads\\edubreezy_web\\edutemp\\src\\app\\api\\mobile\\dashboard\\parent\\route.js", "source_location": "L38", "weight": 1.0}, {"source": "route_get", "target": "route_fetchchildattendance", "relation": "calls", "confidence": "EXTRACTED", "source_file": "C:\\Users\\theco\\Downloads\\edubreezy_web\\edutemp\\src\\app\\api\\mobile\\dashboard\\parent\\route.js", "source_location": "L45", "weight": 1.0}, {"source": "route_get", "target": "route_fetchchildhomework", "relation": "calls", "confidence": "EXTRACTED", "source_file": "C:\\Users\\theco\\Downloads\\edubreezy_web\\edutemp\\src\\app\\api\\mobile\\dashboard\\parent\\route.js", "source_location": "L46", "weight": 1.0}, {"source": "route_get", "target": "route_fetchchildexams", "relation": "calls", "confidence": "EXTRACTED", "source_file": "C:\\Users\\theco\\Downloads\\edubreezy_web\\edutemp\\src\\app\\api\\mobile\\dashboard\\parent\\route.js", "source_location": "L47", "weight": 1.0}, {"source": "route_get", "target": "route_fetchchildfees", "relation": "calls", "confidence": "EXTRACTED", "source_file": "C:\\Users\\theco\\Downloads\\edubreezy_web\\edutemp\\src\\app\\api\\mobile\\dashboard\\parent\\route.js", "source_location": "L48", "weight": 1.0}], "raw_calls": [{"caller_nid": "route_get", "callee": "json", "source_file": "C:\\Users\\theco\\Downloads\\edubreezy_web\\edutemp\\src\\app\\api\\mobile\\dashboard\\parent\\route.js", "source_location": "L18"}, {"caller_nid": "route_get", "callee": "getMonth", "source_file": "C:\\Users\\theco\\Downloads\\edubreezy_web\\edutemp\\src\\app\\api\\mobile\\dashboard\\parent\\route.js", "source_location": "L25"}, {"caller_nid": "route_get", "callee": "getFullYear", "source_file": "C:\\Users\\theco\\Downloads\\edubreezy_web\\edutemp\\src\\app\\api\\mobile\\dashboard\\parent\\route.js", "source_location": "L26"}, {"caller_nid": "route_get", "callee": "all", "source_file": "C:\\Users\\theco\\Downloads\\edubreezy_web\\edutemp\\src\\app\\api\\mobile\\dashboard\\parent\\route.js", "source_location": "L34"}, {"caller_nid": "route_get", "callee": "all", "source_file": "C:\\Users\\theco\\Downloads\\edubreezy_web\\edutemp\\src\\app\\api\\mobile\\dashboard\\parent\\route.js", "source_location": "L44"}, {"caller_nid": "route_get", "callee": "json", "source_file": "C:\\Users\\theco\\Downloads\\edubreezy_web\\edutemp\\src\\app\\api\\mobile\\dashboard\\parent\\route.js", "source_location": "L59"}, {"caller_nid": "route_get", "callee": "error", "source_file": "C:\\Users\\theco\\Downloads\\edubreezy_web\\edutemp\\src\\app\\api\\mobile\\dashboard\\parent\\route.js", "source_location": "L71"}, {"caller_nid": "route_get", "callee": "json", "source_file": "C:\\Users\\theco\\Downloads\\edubreezy_web\\edutemp\\src\\app\\api\\mobile\\dashboard\\parent\\route.js", "source_location": "L72"}, {"caller_nid": "route_fetchchildren", "callee": "findMany", "source_file": "C:\\Users\\theco\\Downloads\\edubreezy_web\\edutemp\\src\\app\\api\\mobile\\dashboard\\parent\\route.js", "source_location": "L83"}, {"caller_nid": "route_fetchchildren", "callee": "map", "source_file": "C:\\Users\\theco\\Downloads\\edubreezy_web\\edutemp\\src\\app\\api\\mobile\\dashboard\\parent\\route.js", "source_location": "L102"}, {"caller_nid": "route_fetchchildren", "callee": "error", "source_file": "C:\\Users\\theco\\Downloads\\edubreezy_web\\edutemp\\src\\app\\api\\mobile\\dashboard\\parent\\route.js", "source_location": "L117"}, {"caller_nid": "route_fetchnotices", "callee": "findMany", "source_file": "C:\\Users\\theco\\Downloads\\edubreezy_web\\edutemp\\src\\app\\api\\mobile\\dashboard\\parent\\route.js", "source_location": "L124"}, {"caller_nid": "route_fetchnotices", "callee": "map", "source_file": "C:\\Users\\theco\\Downloads\\edubreezy_web\\edutemp\\src\\app\\api\\mobile\\dashboard\\parent\\route.js", "source_location": "L151"}, {"caller_nid": "route_fetchnotices", "callee": "error", "source_file": "C:\\Users\\theco\\Downloads\\edubreezy_web\\edutemp\\src\\app\\api\\mobile\\dashboard\\parent\\route.js", "source_location": "L158"}, {"caller_nid": "route_fetchupcomingevents", "callee": "setHours", "source_file": "C:\\Users\\theco\\Downloads\\edubreezy_web\\edutemp\\src\\app\\api\\mobile\\dashboard\\parent\\route.js", "source_location": "L166"}, {"caller_nid": "route_fetchupcomingevents", "callee": "findMany", "source_file": "C:\\Users\\theco\\Downloads\\edubreezy_web\\edutemp\\src\\app\\api\\mobile\\dashboard\\parent\\route.js", "source_location": "L168"}, {"caller_nid": "route_fetchupcomingevents", "callee": "error", "source_file": "C:\\Users\\theco\\Downloads\\edubreezy_web\\edutemp\\src\\app\\api\\mobile\\dashboard\\parent\\route.js", "source_location": "L189"}, {"caller_nid": "route_fetchactiveacademicyear", "callee": "findFirst", "source_file": "C:\\Users\\theco\\Downloads\\edubreezy_web\\edutemp\\src\\app\\api\\mobile\\dashboard\\parent\\route.js", "source_location": "L196"}, {"caller_nid": "route_fetchactiveacademicyear", "callee": "error", "source_file": "C:\\Users\\theco\\Downloads\\edubreezy_web\\edutemp\\src\\app\\api\\mobile\\dashboard\\parent\\route.js", "source_location": "L201"}, {"caller_nid": "route_fetchchildattendance", "callee": "findFirst", "source_file": "C:\\Users\\theco\\Downloads\\edubreezy_web\\edutemp\\src\\app\\api\\mobile\\dashboard\\parent\\route.js", "source_location": "L209"}, {"caller_nid": "route_fetchchildattendance", "callee": "all", "source_file": "C:\\Users\\theco\\Downloads\\edubreezy_web\\edutemp\\src\\app\\api\\mobile\\dashboard\\parent\\route.js", "source_location": "L223"}, {"caller_nid": "route_fetchchildattendance", "callee": "findMany", "source_file": "C:\\Users\\theco\\Downloads\\edubreezy_web\\edutemp\\src\\app\\api\\mobile\\dashboard\\parent\\route.js", "source_location": "L225"}, {"caller_nid": "route_fetchchildattendance", "callee": "findMany", "source_file": "C:\\Users\\theco\\Downloads\\edubreezy_web\\edutemp\\src\\app\\api\\mobile\\dashboard\\parent\\route.js", "source_location": "L234"}, {"caller_nid": "route_fetchchildattendance", "callee": "count", "source_file": "C:\\Users\\theco\\Downloads\\edubreezy_web\\edutemp\\src\\app\\api\\mobile\\dashboard\\parent\\route.js", "source_location": "L242"}, {"caller_nid": "route_fetchchildattendance", "callee": "count", "source_file": "C:\\Users\\theco\\Downloads\\edubreezy_web\\edutemp\\src\\app\\api\\mobile\\dashboard\\parent\\route.js", "source_location": "L249"}, {"caller_nid": "route_fetchchildattendance", "callee": "filter", "source_file": "C:\\Users\\theco\\Downloads\\edubreezy_web\\edutemp\\src\\app\\api\\mobile\\dashboard\\parent\\route.js", "source_location": "L259"}, {"caller_nid": "route_fetchchildattendance", "callee": "filter", "source_file": "C:\\Users\\theco\\Downloads\\edubreezy_web\\edutemp\\src\\app\\api\\mobile\\dashboard\\parent\\route.js", "source_location": "L260"}, {"caller_nid": "route_fetchchildattendance", "callee": "filter", "source_file": "C:\\Users\\theco\\Downloads\\edubreezy_web\\edutemp\\src\\app\\api\\mobile\\dashboard\\parent\\route.js", "source_location": "L264"}, {"caller_nid": "route_fetchchildattendance", "callee": "filter", "source_file": "C:\\Users\\theco\\Downloads\\edubreezy_web\\edutemp\\src\\app\\api\\mobile\\dashboard\\parent\\route.js", "source_location": "L265"}, {"caller_nid": "route_fetchchildattendance", "callee": "round", "source_file": "C:\\Users\\theco\\Downloads\\edubreezy_web\\edutemp\\src\\app\\api\\mobile\\dashboard\\parent\\route.js", "source_location": "L271"}, {"caller_nid": "route_fetchchildattendance", "callee": "round", "source_file": "C:\\Users\\theco\\Downloads\\edubreezy_web\\edutemp\\src\\app\\api\\mobile\\dashboard\\parent\\route.js", "source_location": "L277"}, {"caller_nid": "route_fetchchildattendance", "callee": "error", "source_file": "C:\\Users\\theco\\Downloads\\edubreezy_web\\edutemp\\src\\app\\api\\mobile\\dashboard\\parent\\route.js", "source_location": "L285"}, {"caller_nid": "route_fetchchildhomework", "callee": "findUnique", "source_file": "C:\\Users\\theco\\Downloads\\edubreezy_web\\edutemp\\src\\app\\api\\mobile\\dashboard\\parent\\route.js", "source_location": "L292"}, {"caller_nid": "route_fetchchildhomework", "callee": "findMany", "source_file": "C:\\Users\\theco\\Downloads\\edubreezy_web\\edutemp\\src\\app\\api\\mobile\\dashboard\\parent\\route.js", "source_location": "L299"}, {"caller_nid": "route_fetchchildhomework", "callee": "now", "source_file": "C:\\Users\\theco\\Downloads\\edubreezy_web\\edutemp\\src\\app\\api\\mobile\\dashboard\\parent\\route.js", "source_location": "L306"}, {"caller_nid": "route_fetchchildhomework", "callee": "map", "source_file": "C:\\Users\\theco\\Downloads\\edubreezy_web\\edutemp\\src\\app\\api\\mobile\\dashboard\\parent\\route.js", "source_location": "L319"}, {"caller_nid": "route_fetchchildhomework", "callee": "filter", "source_file": "C:\\Users\\theco\\Downloads\\edubreezy_web\\edutemp\\src\\app\\api\\mobile\\dashboard\\parent\\route.js", "source_location": "L328"}, {"caller_nid": "route_fetchchildhomework", "callee": "error", "source_file": "C:\\Users\\theco\\Downloads\\edubreezy_web\\edutemp\\src\\app\\api\\mobile\\dashboard\\parent\\route.js", "source_location": "L335"}, {"caller_nid": "route_fetchchildexams", "callee": "findMany", "source_file": "C:\\Users\\theco\\Downloads\\edubreezy_web\\edutemp\\src\\app\\api\\mobile\\dashboard\\parent\\route.js", "source_location": "L342"}, {"caller_nid": "route_fetchchildexams", "callee": "findMany", "source_file": "C:\\Users\\theco\\Downloads\\edubreezy_web\\edutemp\\src\\app\\api\\mobile\\dashboard\\parent\\route.js", "source_location": "L360"}, {"caller_nid": "route_fetchchildexams", "callee": "map", "source_file": "C:\\Users\\theco\\Downloads\\edubreezy_web\\edutemp\\src\\app\\api\\mobile\\dashboard\\parent\\route.js", "source_location": "L362"}, {"caller_nid": "route_fetchchildexams", "callee": "forEach", "source_file": "C:\\Users\\theco\\Downloads\\edubreezy_web\\edutemp\\src\\app\\api\\mobile\\dashboard\\parent\\route.js", "source_location": "L369"}, {"caller_nid": "route_fetchchildexams", "callee": "map", "source_file": "C:\\Users\\theco\\Downloads\\edubreezy_web\\edutemp\\src\\app\\api\\mobile\\dashboard\\parent\\route.js", "source_location": "L374"}, {"caller_nid": "route_fetchchildexams", "callee": "filter", "source_file": "C:\\Users\\theco\\Downloads\\edubreezy_web\\edutemp\\src\\app\\api\\mobile\\dashboard\\parent\\route.js", "source_location": "L391"}, {"caller_nid": "route_fetchchildexams", "callee": "round", "source_file": "C:\\Users\\theco\\Downloads\\edubreezy_web\\edutemp\\src\\app\\api\\mobile\\dashboard\\parent\\route.js", "source_location": "L393"}, {"caller_nid": "route_fetchchildexams", "callee": "reduce", "source_file": "C:\\Users\\theco\\Downloads\\edubreezy_web\\edutemp\\src\\app\\api\\mobile\\dashboard\\parent\\route.js", "source_location": "L393"}, {"caller_nid": "route_fetchchildexams", "callee": "error", "source_file": "C:\\Users\\theco\\Downloads\\edubreezy_web\\edutemp\\src\\app\\api\\mobile\\dashboard\\parent\\route.js", "source_location": "L401"}, {"caller_nid": "route_fetchchildfees", "callee": "findFirst", "source_file": "C:\\Users\\theco\\Downloads\\edubreezy_web\\edutemp\\src\\app\\api\\mobile\\dashboard\\parent\\route.js", "source_location": "L410"}, {"caller_nid": "route_fetchchildfees", "callee": "error", "source_file": "C:\\Users\\theco\\Downloads\\edubreezy_web\\edutemp\\src\\app\\api\\mobile\\dashboard\\parent\\route.js", "source_location": "L422"}]}