{"nodes": [{"id": "c_users_theco_downloads_edubreezy_web_edutemp_src_components_dashboard_welcomebanner_jsx", "label": "WelcomeBanner.jsx", "file_type": "code", "source_file": "C:\\Users\\theco\\Downloads\\edubreezy_web\\edutemp\\src\\components\\dashboard\\WelcomeBanner.jsx", "source_location": "L1"}, {"id": "welcomebanner_usetypingeffect", "label": "useTypingEffect()", "file_type": "code", "source_file": "C:\\Users\\theco\\Downloads\\edubreezy_web\\edutemp\\src\\components\\dashboard\\WelcomeBanner.jsx", "source_location": "L9"}, {"id": "welcomebanner_getinitials", "label": "getInitials()", "file_type": "code", "source_file": "C:\\Users\\theco\\Downloads\\edubreezy_web\\edutemp\\src\\components\\dashboard\\WelcomeBanner.jsx", "source_location": "L41"}, {"id": "welcomebanner_welcomebanner", "label": "WelcomeBanner()", "file_type": "code", "source_file": "C:\\Users\\theco\\Downloads\\edubreezy_web\\edutemp\\src\\components\\dashboard\\WelcomeBanner.jsx", "source_location": "L48"}], "edges": [{"source": "c_users_theco_downloads_edubreezy_web_edutemp_src_components_dashboard_welcomebanner_jsx", "target": "react", "relation": "imports_from", "confidence": "EXTRACTED", "source_file": "C:\\Users\\theco\\Downloads\\edubreezy_web\\edutemp\\src\\components\\dashboard\\WelcomeBanner.jsx", "source_location": "L2", "weight": 1.0}, {"source": "c_users_theco_downloads_edubreezy_web_edutemp_src_components_dashboard_welcomebanner_jsx", "target": "lucide_react", "relation": "imports_from", "confidence": "EXTRACTED", "source_file": "C:\\Users\\theco\\Downloads\\edubreezy_web\\edutemp\\src\\components\\dashboard\\WelcomeBanner.jsx", "source_location": "L3", "weight": 1.0}, {"source": "c_users_theco_downloads_edubreezy_web_edutemp_src_components_dashboard_welcomebanner_jsx", "target": "usedashboardcontext", "relation": "imports_from", "confidence": "EXTRACTED", "source_file": "C:\\Users\\theco\\Downloads\\edubreezy_web\\edutemp\\src\\components\\dashboard\\WelcomeBanner.jsx", "source_location": "L4", "weight": 1.0}, {"source": "c_users_theco_downloads_edubreezy_web_edutemp_src_components_dashboard_welcomebanner_jsx", "target": "useaiinsights", "relation": "imports_from", "confidence": "EXTRACTED", "source_file": "C:\\Users\\theco\\Downloads\\edubreezy_web\\edutemp\\src\\components\\dashboard\\WelcomeBanner.jsx", "source_location": "L5", "weight": 1.0}, {"source": "c_users_theco_downloads_edubreezy_web_edutemp_src_components_dashboard_welcomebanner_jsx", "target": "image", "relation": "imports_from", "confidence": "EXTRACTED", "source_file": "C:\\Users\\theco\\Downloads\\edubreezy_web\\edutemp\\src\\components\\dashboard\\WelcomeBanner.jsx", "source_location": "L6", "weight": 1.0}, {"source": "c_users_theco_downloads_edubreezy_web_edutemp_src_components_dashboard_welcomebanner_jsx", "target": "welcomebanner_usetypingeffect", "relation": "contains", "confidence": "EXTRACTED", "source_file": "C:\\Users\\theco\\Downloads\\edubreezy_web\\edutemp\\src\\components\\dashboard\\WelcomeBanner.jsx", "source_location": "L9", "weight": 1.0}, {"source": "c_users_theco_downloads_edubreezy_web_edutemp_src_components_dashboard_welcomebanner_jsx", "target": "welcomebanner_getinitials", "relation": "contains", "confidence": "EXTRACTED", "source_file": "C:\\Users\\theco\\Downloads\\edubreezy_web\\edutemp\\src\\components\\dashboard\\WelcomeBanner.jsx", "source_location": "L41", "weight": 1.0}, {"source": "c_users_theco_downloads_edubreezy_web_edutemp_src_components_dashboard_welcomebanner_jsx", "target": "welcomebanner_welcomebanner", "relation": "contains", "confidence": "EXTRACTED", "source_file": "C:\\Users\\theco\\Downloads\\edubreezy_web\\edutemp\\src\\components\\dashboard\\WelcomeBanner.jsx", "source_location": "L48", "weight": 1.0}, {"source": "welcomebanner_welcomebanner", "target": "welcomebanner_usetypingeffect", "relation": "calls", "confidence": "EXTRACTED", "source_file": "C:\\Users\\theco\\Downloads\\edubreezy_web\\edutemp\\src\\components\\dashboard\\WelcomeBanner.jsx", "source_location": "L107", "weight": 1.0}, {"source": "welcomebanner_welcomebanner", "target": "welcomebanner_getinitials", "relation": "calls", "confidence": "EXTRACTED", "source_file": "C:\\Users\\theco\\Downloads\\edubreezy_web\\edutemp\\src\\components\\dashboard\\WelcomeBanner.jsx", "source_location": "L113", "weight": 1.0}], "raw_calls": [{"caller_nid": "welcomebanner_usetypingeffect", "callee": "useState", "source_file": "C:\\Users\\theco\\Downloads\\edubreezy_web\\edutemp\\src\\components\\dashboard\\WelcomeBanner.jsx", "source_location": "L10"}, {"caller_nid": "welcomebanner_usetypingeffect", "callee": "useState", "source_file": "C:\\Users\\theco\\Downloads\\edubreezy_web\\edutemp\\src\\components\\dashboard\\WelcomeBanner.jsx", "source_location": "L11"}, {"caller_nid": "welcomebanner_usetypingeffect", "callee": "useEffect", "source_file": "C:\\Users\\theco\\Downloads\\edubreezy_web\\edutemp\\src\\components\\dashboard\\WelcomeBanner.jsx", "source_location": "L13"}, {"caller_nid": "welcomebanner_getinitials", "callee": "split", "source_file": "C:\\Users\\theco\\Downloads\\edubreezy_web\\edutemp\\src\\components\\dashboard\\WelcomeBanner.jsx", "source_location": "L43"}, {"caller_nid": "welcomebanner_getinitials", "callee": "trim", "source_file": "C:\\Users\\theco\\Downloads\\edubreezy_web\\edutemp\\src\\components\\dashboard\\WelcomeBanner.jsx", "source_location": "L43"}, {"caller_nid": "welcomebanner_getinitials", "callee": "toUpperCase", "source_file": "C:\\Users\\theco\\Downloads\\edubreezy_web\\edutemp\\src\\components\\dashboard\\WelcomeBanner.jsx", "source_location": "L44"}, {"caller_nid": "welcomebanner_getinitials", "callee": "charAt", "source_file": "C:\\Users\\theco\\Downloads\\edubreezy_web\\edutemp\\src\\components\\dashboard\\WelcomeBanner.jsx", "source_location": "L44"}, {"caller_nid": "welcomebanner_getinitials", "callee": "toUpperCase", "source_file": "C:\\Users\\theco\\Downloads\\edubreezy_web\\edutemp\\src\\components\\dashboard\\WelcomeBanner.jsx", "source_location": "L45"}, {"caller_nid": "welcomebanner_getinitials", "callee": "charAt", "source_file": "C:\\Users\\theco\\Downloads\\edubreezy_web\\edutemp\\src\\components\\dashboard\\WelcomeBanner.jsx", "source_location": "L45"}, {"caller_nid": "welcomebanner_getinitials", "callee": "charAt", "source_file": "C:\\Users\\theco\\Downloads\\edubreezy_web\\edutemp\\src\\components\\dashboard\\WelcomeBanner.jsx", "source_location": "L45"}, {"caller_nid": "welcomebanner_welcomebanner", "callee": "useState", "source_file": "C:\\Users\\theco\\Downloads\\edubreezy_web\\edutemp\\src\\components\\dashboard\\WelcomeBanner.jsx", "source_location": "L49"}, {"caller_nid": "welcomebanner_welcomebanner", "callee": "useDashboardContext", "source_file": "C:\\Users\\theco\\Downloads\\edubreezy_web\\edutemp\\src\\components\\dashboard\\WelcomeBanner.jsx", "source_location": "L52"}, {"caller_nid": "welcomebanner_welcomebanner", "callee": "useAiInsights", "source_file": "C:\\Users\\theco\\Downloads\\edubreezy_web\\edutemp\\src\\components\\dashboard\\WelcomeBanner.jsx", "source_location": "L53"}, {"caller_nid": "welcomebanner_welcomebanner", "callee": "useEffect", "source_file": "C:\\Users\\theco\\Downloads\\edubreezy_web\\edutemp\\src\\components\\dashboard\\WelcomeBanner.jsx", "source_location": "L56"}, {"caller_nid": "welcomebanner_welcomebanner", "callee": "useMemo", "source_file": "C:\\Users\\theco\\Downloads\\edubreezy_web\\edutemp\\src\\components\\dashboard\\WelcomeBanner.jsx", "source_location": "L70"}, {"caller_nid": "welcomebanner_welcomebanner", "callee": "split", "source_file": "C:\\Users\\theco\\Downloads\\edubreezy_web\\edutemp\\src\\components\\dashboard\\WelcomeBanner.jsx", "source_location": "L109"}, {"caller_nid": "welcomebanner_welcomebanner", "callee": "toUpperCase", "source_file": "C:\\Users\\theco\\Downloads\\edubreezy_web\\edutemp\\src\\components\\dashboard\\WelcomeBanner.jsx", "source_location": "L199"}]}