{"nodes": [{"id": "c_users_theco_downloads_edubreezy_web_edutemp_src_app_api_schools_schoolid_hpc_stage_templates_route_js", "label": "route.js", "file_type": "code", "source_file": "C:\\Users\\theco\\Downloads\\edubreezy_web\\edutemp\\src\\app\\api\\schools\\[schoolId]\\hpc\\stage-templates\\route.js", "source_location": "L1"}, {"id": "route_get", "label": "GET()", "file_type": "code", "source_file": "C:\\Users\\theco\\Downloads\\edubreezy_web\\edutemp\\src\\app\\api\\schools\\[schoolId]\\hpc\\stage-templates\\route.js", "source_location": "L65"}, {"id": "route_post", "label": "POST()", "file_type": "code", "source_file": "C:\\Users\\theco\\Downloads\\edubreezy_web\\edutemp\\src\\app\\api\\schools\\[schoolId]\\hpc\\stage-templates\\route.js", "source_location": "L94"}, {"id": "route_put", "label": "PUT()", "file_type": "code", "source_file": "C:\\Users\\theco\\Downloads\\edubreezy_web\\edutemp\\src\\app\\api\\schools\\[schoolId]\\hpc\\stage-templates\\route.js", "source_location": "L180"}], "edges": [{"source": "c_users_theco_downloads_edubreezy_web_edutemp_src_app_api_schools_schoolid_hpc_stage_templates_route_js", "target": "server", "relation": "imports_from", "confidence": "EXTRACTED", "source_file": "C:\\Users\\theco\\Downloads\\edubreezy_web\\edutemp\\src\\app\\api\\schools\\[schoolId]\\hpc\\stage-templates\\route.js", "source_location": "L1", "weight": 1.0}, {"source": "c_users_theco_downloads_edubreezy_web_edutemp_src_app_api_schools_schoolid_hpc_stage_templates_route_js", "target": "prisma", "relation": "imports_from", "confidence": "EXTRACTED", "source_file": "C:\\Users\\theco\\Downloads\\edubreezy_web\\edutemp\\src\\app\\api\\schools\\[schoolId]\\hpc\\stage-templates\\route.js", "source_location": "L2", "weight": 1.0}, {"source": "c_users_theco_downloads_edubreezy_web_edutemp_src_app_api_schools_schoolid_hpc_stage_templates_route_js", "target": "route_get", "relation": "contains", "confidence": "EXTRACTED", "source_file": "C:\\Users\\theco\\Downloads\\edubreezy_web\\edutemp\\src\\app\\api\\schools\\[schoolId]\\hpc\\stage-templates\\route.js", "source_location": "L65", "weight": 1.0}, {"source": "c_users_theco_downloads_edubreezy_web_edutemp_src_app_api_schools_schoolid_hpc_stage_templates_route_js", "target": "route_post", "relation": "contains", "confidence": "EXTRACTED", "source_file": "C:\\Users\\theco\\Downloads\\edubreezy_web\\edutemp\\src\\app\\api\\schools\\[schoolId]\\hpc\\stage-templates\\route.js", "source_location": "L94", "weight": 1.0}, {"source": "c_users_theco_downloads_edubreezy_web_edutemp_src_app_api_schools_schoolid_hpc_stage_templates_route_js", "target": "route_put", "relation": "contains", "confidence": "EXTRACTED", "source_file": "C:\\Users\\theco\\Downloads\\edubreezy_web\\edutemp\\src\\app\\api\\schools\\[schoolId]\\hpc\\stage-templates\\route.js", "source_location": "L180", "weight": 1.0}], "raw_calls": [{"caller_nid": "route_get", "callee": "json", "source_file": "C:\\Users\\theco\\Downloads\\edubreezy_web\\edutemp\\src\\app\\api\\schools\\[schoolId]\\hpc\\stage-templates\\route.js", "source_location": "L70"}, {"caller_nid": "route_get", "callee": "findMany", "source_file": "C:\\Users\\theco\\Downloads\\edubreezy_web\\edutemp\\src\\app\\api\\schools\\[schoolId]\\hpc\\stage-templates\\route.js", "source_location": "L74"}, {"caller_nid": "route_get", "callee": "json", "source_file": "C:\\Users\\theco\\Downloads\\edubreezy_web\\edutemp\\src\\app\\api\\schools\\[schoolId]\\hpc\\stage-templates\\route.js", "source_location": "L79"}, {"caller_nid": "route_get", "callee": "error", "source_file": "C:\\Users\\theco\\Downloads\\edubreezy_web\\edutemp\\src\\app\\api\\schools\\[schoolId]\\hpc\\stage-templates\\route.js", "source_location": "L85"}, {"caller_nid": "route_get", "callee": "json", "source_file": "C:\\Users\\theco\\Downloads\\edubreezy_web\\edutemp\\src\\app\\api\\schools\\[schoolId]\\hpc\\stage-templates\\route.js", "source_location": "L86"}, {"caller_nid": "route_post", "callee": "json", "source_file": "C:\\Users\\theco\\Downloads\\edubreezy_web\\edutemp\\src\\app\\api\\schools\\[schoolId]\\hpc\\stage-templates\\route.js", "source_location": "L97"}, {"caller_nid": "route_post", "callee": "json", "source_file": "C:\\Users\\theco\\Downloads\\edubreezy_web\\edutemp\\src\\app\\api\\schools\\[schoolId]\\hpc\\stage-templates\\route.js", "source_location": "L114"}, {"caller_nid": "route_post", "callee": "includes", "source_file": "C:\\Users\\theco\\Downloads\\edubreezy_web\\edutemp\\src\\app\\api\\schools\\[schoolId]\\hpc\\stage-templates\\route.js", "source_location": "L119"}, {"caller_nid": "route_post", "callee": "json", "source_file": "C:\\Users\\theco\\Downloads\\edubreezy_web\\edutemp\\src\\app\\api\\schools\\[schoolId]\\hpc\\stage-templates\\route.js", "source_location": "L120"}, {"caller_nid": "route_post", "callee": "abs", "source_file": "C:\\Users\\theco\\Downloads\\edubreezy_web\\edutemp\\src\\app\\api\\schools\\[schoolId]\\hpc\\stage-templates\\route.js", "source_location": "L125"}, {"caller_nid": "route_post", "callee": "json", "source_file": "C:\\Users\\theco\\Downloads\\edubreezy_web\\edutemp\\src\\app\\api\\schools\\[schoolId]\\hpc\\stage-templates\\route.js", "source_location": "L126"}, {"caller_nid": "route_post", "callee": "upsert", "source_file": "C:\\Users\\theco\\Downloads\\edubreezy_web\\edutemp\\src\\app\\api\\schools\\[schoolId]\\hpc\\stage-templates\\route.js", "source_location": "L133"}, {"caller_nid": "route_post", "callee": "json", "source_file": "C:\\Users\\theco\\Downloads\\edubreezy_web\\edutemp\\src\\app\\api\\schools\\[schoolId]\\hpc\\stage-templates\\route.js", "source_location": "L165"}, {"caller_nid": "route_post", "callee": "error", "source_file": "C:\\Users\\theco\\Downloads\\edubreezy_web\\edutemp\\src\\app\\api\\schools\\[schoolId]\\hpc\\stage-templates\\route.js", "source_location": "L171"}, {"caller_nid": "route_post", "callee": "json", "source_file": "C:\\Users\\theco\\Downloads\\edubreezy_web\\edutemp\\src\\app\\api\\schools\\[schoolId]\\hpc\\stage-templates\\route.js", "source_location": "L172"}, {"caller_nid": "route_put", "callee": "json", "source_file": "C:\\Users\\theco\\Downloads\\edubreezy_web\\edutemp\\src\\app\\api\\schools\\[schoolId]\\hpc\\stage-templates\\route.js", "source_location": "L185"}, {"caller_nid": "route_put", "callee": "entries", "source_file": "C:\\Users\\theco\\Downloads\\edubreezy_web\\edutemp\\src\\app\\api\\schools\\[schoolId]\\hpc\\stage-templates\\route.js", "source_location": "L191"}, {"caller_nid": "route_put", "callee": "upsert", "source_file": "C:\\Users\\theco\\Downloads\\edubreezy_web\\edutemp\\src\\app\\api\\schools\\[schoolId]\\hpc\\stage-templates\\route.js", "source_location": "L192"}, {"caller_nid": "route_put", "callee": "push", "source_file": "C:\\Users\\theco\\Downloads\\edubreezy_web\\edutemp\\src\\app\\api\\schools\\[schoolId]\\hpc\\stage-templates\\route.js", "source_location": "L210"}, {"caller_nid": "route_put", "callee": "json", "source_file": "C:\\Users\\theco\\Downloads\\edubreezy_web\\edutemp\\src\\app\\api\\schools\\[schoolId]\\hpc\\stage-templates\\route.js", "source_location": "L213"}, {"caller_nid": "route_put", "callee": "error", "source_file": "C:\\Users\\theco\\Downloads\\edubreezy_web\\edutemp\\src\\app\\api\\schools\\[schoolId]\\hpc\\stage-templates\\route.js", "source_location": "L219"}, {"caller_nid": "route_put", "callee": "json", "source_file": "C:\\Users\\theco\\Downloads\\edubreezy_web\\edutemp\\src\\app\\api\\schools\\[schoolId]\\hpc\\stage-templates\\route.js", "source_location": "L220"}]}