{"nodes": [{"id": "c_users_theco_downloads_edubreezy_web_edutemp_src_app_api_auth_check_rate_limit_route_js", "label": "route.js", "file_type": "code", "source_file": "C:\\Users\\theco\\Downloads\\edubreezy_web\\edutemp\\src\\app\\api\\auth\\check-rate-limit\\route.js", "source_location": "L1"}, {"id": "route_getclientip", "label": "getClientIP()", "file_type": "code", "source_file": "C:\\Users\\theco\\Downloads\\edubreezy_web\\edutemp\\src\\app\\api\\auth\\check-rate-limit\\route.js", "source_location": "L5"}, {"id": "route_get", "label": "GET()", "file_type": "code", "source_file": "C:\\Users\\theco\\Downloads\\edubreezy_web\\edutemp\\src\\app\\api\\auth\\check-rate-limit\\route.js", "source_location": "L20"}], "edges": [{"source": "c_users_theco_downloads_edubreezy_web_edutemp_src_app_api_auth_check_rate_limit_route_js", "target": "server", "relation": "imports_from", "confidence": "EXTRACTED", "source_file": "C:\\Users\\theco\\Downloads\\edubreezy_web\\edutemp\\src\\app\\api\\auth\\check-rate-limit\\route.js", "source_location": "L1", "weight": 1.0}, {"source": "c_users_theco_downloads_edubreezy_web_edutemp_src_app_api_auth_check_rate_limit_route_js", "target": "rate_limit", "relation": "imports_from", "confidence": "EXTRACTED", "source_file": "C:\\Users\\theco\\Downloads\\edubreezy_web\\edutemp\\src\\app\\api\\auth\\check-rate-limit\\route.js", "source_location": "L2", "weight": 1.0}, {"source": "c_users_theco_downloads_edubreezy_web_edutemp_src_app_api_auth_check_rate_limit_route_js", "target": "route_getclientip", "relation": "contains", "confidence": "EXTRACTED", "source_file": "C:\\Users\\theco\\Downloads\\edubreezy_web\\edutemp\\src\\app\\api\\auth\\check-rate-limit\\route.js", "source_location": "L5", "weight": 1.0}, {"source": "c_users_theco_downloads_edubreezy_web_edutemp_src_app_api_auth_check_rate_limit_route_js", "target": "route_get", "relation": "contains", "confidence": "EXTRACTED", "source_file": "C:\\Users\\theco\\Downloads\\edubreezy_web\\edutemp\\src\\app\\api\\auth\\check-rate-limit\\route.js", "source_location": "L20", "weight": 1.0}, {"source": "route_getclientip", "target": "route_get", "relation": "calls", "confidence": "EXTRACTED", "source_file": "C:\\Users\\theco\\Downloads\\edubreezy_web\\edutemp\\src\\app\\api\\auth\\check-rate-limit\\route.js", "source_location": "L6", "weight": 1.0}, {"source": "route_get", "target": "route_getclientip", "relation": "calls", "confidence": "EXTRACTED", "source_file": "C:\\Users\\theco\\Downloads\\edubreezy_web\\edutemp\\src\\app\\api\\auth\\check-rate-limit\\route.js", "source_location": "L22", "weight": 1.0}], "raw_calls": [{"caller_nid": "route_getclientip", "callee": "trim", "source_file": "C:\\Users\\theco\\Downloads\\edubreezy_web\\edutemp\\src\\app\\api\\auth\\check-rate-limit\\route.js", "source_location": "L10"}, {"caller_nid": "route_getclientip", "callee": "split", "source_file": "C:\\Users\\theco\\Downloads\\edubreezy_web\\edutemp\\src\\app\\api\\auth\\check-rate-limit\\route.js", "source_location": "L10"}, {"caller_nid": "route_get", "callee": "isIPBlocked", "source_file": "C:\\Users\\theco\\Downloads\\edubreezy_web\\edutemp\\src\\app\\api\\auth\\check-rate-limit\\route.js", "source_location": "L24"}, {"caller_nid": "route_get", "callee": "getRemainingAttempts", "source_file": "C:\\Users\\theco\\Downloads\\edubreezy_web\\edutemp\\src\\app\\api\\auth\\check-rate-limit\\route.js", "source_location": "L25"}, {"caller_nid": "route_get", "callee": "json", "source_file": "C:\\Users\\theco\\Downloads\\edubreezy_web\\edutemp\\src\\app\\api\\auth\\check-rate-limit\\route.js", "source_location": "L27"}, {"caller_nid": "route_get", "callee": "error", "source_file": "C:\\Users\\theco\\Downloads\\edubreezy_web\\edutemp\\src\\app\\api\\auth\\check-rate-limit\\route.js", "source_location": "L32"}, {"caller_nid": "route_get", "callee": "json", "source_file": "C:\\Users\\theco\\Downloads\\edubreezy_web\\edutemp\\src\\app\\api\\auth\\check-rate-limit\\route.js", "source_location": "L33"}]}