{"nodes": [{"id": "c_users_theco_downloads_edubreezy_web_edutemp_src_components_dashboard_widgets_statsoverviewwidget_jsx", "label": "StatsOverviewWidget.jsx", "file_type": "code", "source_file": "C:\\Users\\theco\\Downloads\\edubreezy_web\\edutemp\\src\\components\\dashboard\\widgets\\StatsOverviewWidget.jsx", "source_location": "L1"}, {"id": "statsoverviewwidget_fetchstats", "label": "fetchStats()", "file_type": "code", "source_file": "C:\\Users\\theco\\Downloads\\edubreezy_web\\edutemp\\src\\components\\dashboard\\widgets\\StatsOverviewWidget.jsx", "source_location": "L6"}, {"id": "statsoverviewwidget_statsoverviewwidget", "label": "StatsOverviewWidget()", "file_type": "code", "source_file": "C:\\Users\\theco\\Downloads\\edubreezy_web\\edutemp\\src\\components\\dashboard\\widgets\\StatsOverviewWidget.jsx", "source_location": "L28"}], "edges": [{"source": "c_users_theco_downloads_edubreezy_web_edutemp_src_components_dashboard_widgets_statsoverviewwidget_jsx", "target": "react_query", "relation": "imports_from", "confidence": "EXTRACTED", "source_file": "C:\\Users\\theco\\Downloads\\edubreezy_web\\edutemp\\src\\components\\dashboard\\widgets\\StatsOverviewWidget.jsx", "source_location": "L2", "weight": 1.0}, {"source": "c_users_theco_downloads_edubreezy_web_edutemp_src_components_dashboard_widgets_statsoverviewwidget_jsx", "target": "lucide_react", "relation": "imports_from", "confidence": "EXTRACTED", "source_file": "C:\\Users\\theco\\Downloads\\edubreezy_web\\edutemp\\src\\components\\dashboard\\widgets\\StatsOverviewWidget.jsx", "source_location": "L3", "weight": 1.0}, {"source": "c_users_theco_downloads_edubreezy_web_edutemp_src_components_dashboard_widgets_statsoverviewwidget_jsx", "target": "skeleton", "relation": "imports_from", "confidence": "EXTRACTED", "source_file": "C:\\Users\\theco\\Downloads\\edubreezy_web\\edutemp\\src\\components\\dashboard\\widgets\\StatsOverviewWidget.jsx", "source_location": "L4", "weight": 1.0}, {"source": "c_users_theco_downloads_edubreezy_web_edutemp_src_components_dashboard_widgets_statsoverviewwidget_jsx", "target": "statsoverviewwidget_fetchstats", "relation": "contains", "confidence": "EXTRACTED", "source_file": "C:\\Users\\theco\\Downloads\\edubreezy_web\\edutemp\\src\\components\\dashboard\\widgets\\StatsOverviewWidget.jsx", "source_location": "L6", "weight": 1.0}, {"source": "c_users_theco_downloads_edubreezy_web_edutemp_src_components_dashboard_widgets_statsoverviewwidget_jsx", "target": "statsoverviewwidget_statsoverviewwidget", "relation": "contains", "confidence": "EXTRACTED", "source_file": "C:\\Users\\theco\\Downloads\\edubreezy_web\\edutemp\\src\\components\\dashboard\\widgets\\StatsOverviewWidget.jsx", "source_location": "L28", "weight": 1.0}], "raw_calls": [{"caller_nid": "statsoverviewwidget_fetchstats", "callee": "fetch", "source_file": "C:\\Users\\theco\\Downloads\\edubreezy_web\\edutemp\\src\\components\\dashboard\\widgets\\StatsOverviewWidget.jsx", "source_location": "L10"}, {"caller_nid": "statsoverviewwidget_fetchstats", "callee": "json", "source_file": "C:\\Users\\theco\\Downloads\\edubreezy_web\\edutemp\\src\\components\\dashboard\\widgets\\StatsOverviewWidget.jsx", "source_location": "L11"}, {"caller_nid": "statsoverviewwidget_fetchstats", "callee": "fetch", "source_file": "C:\\Users\\theco\\Downloads\\edubreezy_web\\edutemp\\src\\components\\dashboard\\widgets\\StatsOverviewWidget.jsx", "source_location": "L14"}, {"caller_nid": "statsoverviewwidget_fetchstats", "callee": "json", "source_file": "C:\\Users\\theco\\Downloads\\edubreezy_web\\edutemp\\src\\components\\dashboard\\widgets\\StatsOverviewWidget.jsx", "source_location": "L15"}, {"caller_nid": "statsoverviewwidget_fetchstats", "callee": "fetch", "source_file": "C:\\Users\\theco\\Downloads\\edubreezy_web\\edutemp\\src\\components\\dashboard\\widgets\\StatsOverviewWidget.jsx", "source_location": "L18"}, {"caller_nid": "statsoverviewwidget_fetchstats", "callee": "json", "source_file": "C:\\Users\\theco\\Downloads\\edubreezy_web\\edutemp\\src\\components\\dashboard\\widgets\\StatsOverviewWidget.jsx", "source_location": "L19"}, {"caller_nid": "statsoverviewwidget_statsoverviewwidget", "callee": "useQuery", "source_file": "C:\\Users\\theco\\Downloads\\edubreezy_web\\edutemp\\src\\components\\dashboard\\widgets\\StatsOverviewWidget.jsx", "source_location": "L29"}, {"caller_nid": "statsoverviewwidget_statsoverviewwidget", "callee": "map", "source_file": "C:\\Users\\theco\\Downloads\\edubreezy_web\\edutemp\\src\\components\\dashboard\\widgets\\StatsOverviewWidget.jsx", "source_location": "L38"}, {"caller_nid": "statsoverviewwidget_statsoverviewwidget", "callee": "map", "source_file": "C:\\Users\\theco\\Downloads\\edubreezy_web\\edutemp\\src\\components\\dashboard\\widgets\\StatsOverviewWidget.jsx", "source_location": "L72"}]}