{"nodes": [{"id": "c_users_theco_downloads_edubreezy_web_edutemp_src_components_teachers_shiftmanager_jsx", "label": "ShiftManager.jsx", "file_type": "code", "source_file": "C:\\Users\\theco\\Downloads\\edubreezy_web\\edutemp\\src\\components\\teachers\\ShiftManager.jsx", "source_location": "L1"}, {"id": "shiftmanager_shiftmanager", "label": "ShiftManager()", "file_type": "code", "source_file": "C:\\Users\\theco\\Downloads\\edubreezy_web\\edutemp\\src\\components\\teachers\\ShiftManager.jsx", "source_location": "L33"}], "edges": [{"source": "c_users_theco_downloads_edubreezy_web_edutemp_src_components_teachers_shiftmanager_jsx", "target": "react", "relation": "imports_from", "confidence": "EXTRACTED", "source_file": "C:\\Users\\theco\\Downloads\\edubreezy_web\\edutemp\\src\\components\\teachers\\ShiftManager.jsx", "source_location": "L3", "weight": 1.0}, {"source": "c_users_theco_downloads_edubreezy_web_edutemp_src_components_teachers_shiftmanager_jsx", "target": "axios", "relation": "imports_from", "confidence": "EXTRACTED", "source_file": "C:\\Users\\theco\\Downloads\\edubreezy_web\\edutemp\\src\\components\\teachers\\ShiftManager.jsx", "source_location": "L4", "weight": 1.0}, {"source": "c_users_theco_downloads_edubreezy_web_edutemp_src_components_teachers_shiftmanager_jsx", "target": "date_fns", "relation": "imports_from", "confidence": "EXTRACTED", "source_file": "C:\\Users\\theco\\Downloads\\edubreezy_web\\edutemp\\src\\components\\teachers\\ShiftManager.jsx", "source_location": "L5", "weight": 1.0}, {"source": "c_users_theco_downloads_edubreezy_web_edutemp_src_components_teachers_shiftmanager_jsx", "target": "calendar", "relation": "imports_from", "confidence": "EXTRACTED", "source_file": "C:\\Users\\theco\\Downloads\\edubreezy_web\\edutemp\\src\\components\\teachers\\ShiftManager.jsx", "source_location": "L6", "weight": 1.0}, {"source": "c_users_theco_downloads_edubreezy_web_edutemp_src_components_teachers_shiftmanager_jsx", "target": "card", "relation": "imports_from", "confidence": "EXTRACTED", "source_file": "C:\\Users\\theco\\Downloads\\edubreezy_web\\edutemp\\src\\components\\teachers\\ShiftManager.jsx", "source_location": "L7", "weight": 1.0}, {"source": "c_users_theco_downloads_edubreezy_web_edutemp_src_components_teachers_shiftmanager_jsx", "target": "button", "relation": "imports_from", "confidence": "EXTRACTED", "source_file": "C:\\Users\\theco\\Downloads\\edubreezy_web\\edutemp\\src\\components\\teachers\\ShiftManager.jsx", "source_location": "L8", "weight": 1.0}, {"source": "c_users_theco_downloads_edubreezy_web_edutemp_src_components_teachers_shiftmanager_jsx", "target": "badge", "relation": "imports_from", "confidence": "EXTRACTED", "source_file": "C:\\Users\\theco\\Downloads\\edubreezy_web\\edutemp\\src\\components\\teachers\\ShiftManager.jsx", "source_location": "L9", "weight": 1.0}, {"source": "c_users_theco_downloads_edubreezy_web_edutemp_src_components_teachers_shiftmanager_jsx", "target": "dialog", "relation": "imports_from", "confidence": "EXTRACTED", "source_file": "C:\\Users\\theco\\Downloads\\edubreezy_web\\edutemp\\src\\components\\teachers\\ShiftManager.jsx", "source_location": "L10", "weight": 1.0}, {"source": "c_users_theco_downloads_edubreezy_web_edutemp_src_components_teachers_shiftmanager_jsx", "target": "select", "relation": "imports_from", "confidence": "EXTRACTED", "source_file": "C:\\Users\\theco\\Downloads\\edubreezy_web\\edutemp\\src\\components\\teachers\\ShiftManager.jsx", "source_location": "L16", "weight": 1.0}, {"source": "c_users_theco_downloads_edubreezy_web_edutemp_src_components_teachers_shiftmanager_jsx", "target": "alert", "relation": "imports_from", "confidence": "EXTRACTED", "source_file": "C:\\Users\\theco\\Downloads\\edubreezy_web\\edutemp\\src\\components\\teachers\\ShiftManager.jsx", "source_location": "L23", "weight": 1.0}, {"source": "c_users_theco_downloads_edubreezy_web_edutemp_src_components_teachers_shiftmanager_jsx", "target": "label", "relation": "imports_from", "confidence": "EXTRACTED", "source_file": "C:\\Users\\theco\\Downloads\\edubreezy_web\\edutemp\\src\\components\\teachers\\ShiftManager.jsx", "source_location": "L27", "weight": 1.0}, {"source": "c_users_theco_downloads_edubreezy_web_edutemp_src_components_teachers_shiftmanager_jsx", "target": "input", "relation": "imports_from", "confidence": "EXTRACTED", "source_file": "C:\\Users\\theco\\Downloads\\edubreezy_web\\edutemp\\src\\components\\teachers\\ShiftManager.jsx", "source_location": "L28", "weight": 1.0}, {"source": "c_users_theco_downloads_edubreezy_web_edutemp_src_components_teachers_shiftmanager_jsx", "target": "sonner", "relation": "imports_from", "confidence": "EXTRACTED", "source_file": "C:\\Users\\theco\\Downloads\\edubreezy_web\\edutemp\\src\\components\\teachers\\ShiftManager.jsx", "source_location": "L29", "weight": 1.0}, {"source": "c_users_theco_downloads_edubreezy_web_edutemp_src_components_teachers_shiftmanager_jsx", "target": "lucide_react", "relation": "imports_from", "confidence": "EXTRACTED", "source_file": "C:\\Users\\theco\\Downloads\\edubreezy_web\\edutemp\\src\\components\\teachers\\ShiftManager.jsx", "source_location": "L30", "weight": 1.0}, {"source": "c_users_theco_downloads_edubreezy_web_edutemp_src_components_teachers_shiftmanager_jsx", "target": "authcontext", "relation": "imports_from", "confidence": "EXTRACTED", "source_file": "C:\\Users\\theco\\Downloads\\edubreezy_web\\edutemp\\src\\components\\teachers\\ShiftManager.jsx", "source_location": "L31", "weight": 1.0}, {"source": "c_users_theco_downloads_edubreezy_web_edutemp_src_components_teachers_shiftmanager_jsx", "target": "shiftmanager_shiftmanager", "relation": "contains", "confidence": "EXTRACTED", "source_file": "C:\\Users\\theco\\Downloads\\edubreezy_web\\edutemp\\src\\components\\teachers\\ShiftManager.jsx", "source_location": "L33", "weight": 1.0}], "raw_calls": [{"caller_nid": "shiftmanager_shiftmanager", "callee": "useAuth", "source_file": "C:\\Users\\theco\\Downloads\\edubreezy_web\\edutemp\\src\\components\\teachers\\ShiftManager.jsx", "source_location": "L34"}, {"caller_nid": "shiftmanager_shiftmanager", "callee": "useState", "source_file": "C:\\Users\\theco\\Downloads\\edubreezy_web\\edutemp\\src\\components\\teachers\\ShiftManager.jsx", "source_location": "L36"}, {"caller_nid": "shiftmanager_shiftmanager", "callee": "useState", "source_file": "C:\\Users\\theco\\Downloads\\edubreezy_web\\edutemp\\src\\components\\teachers\\ShiftManager.jsx", "source_location": "L37"}, {"caller_nid": "shiftmanager_shiftmanager", "callee": "useState", "source_file": "C:\\Users\\theco\\Downloads\\edubreezy_web\\edutemp\\src\\components\\teachers\\ShiftManager.jsx", "source_location": "L38"}, {"caller_nid": "shiftmanager_shiftmanager", "callee": "useState", "source_file": "C:\\Users\\theco\\Downloads\\edubreezy_web\\edutemp\\src\\components\\teachers\\ShiftManager.jsx", "source_location": "L39"}, {"caller_nid": "shiftmanager_shiftmanager", "callee": "useState", "source_file": "C:\\Users\\theco\\Downloads\\edubreezy_web\\edutemp\\src\\components\\teachers\\ShiftManager.jsx", "source_location": "L40"}, {"caller_nid": "shiftmanager_shiftmanager", "callee": "useState", "source_file": "C:\\Users\\theco\\Downloads\\edubreezy_web\\edutemp\\src\\components\\teachers\\ShiftManager.jsx", "source_location": "L41"}, {"caller_nid": "shiftmanager_shiftmanager", "callee": "useState", "source_file": "C:\\Users\\theco\\Downloads\\edubreezy_web\\edutemp\\src\\components\\teachers\\ShiftManager.jsx", "source_location": "L42"}, {"caller_nid": "shiftmanager_shiftmanager", "callee": "useState", "source_file": "C:\\Users\\theco\\Downloads\\edubreezy_web\\edutemp\\src\\components\\teachers\\ShiftManager.jsx", "source_location": "L43"}, {"caller_nid": "shiftmanager_shiftmanager", "callee": "useState", "source_file": "C:\\Users\\theco\\Downloads\\edubreezy_web\\edutemp\\src\\components\\teachers\\ShiftManager.jsx", "source_location": "L44"}, {"caller_nid": "shiftmanager_shiftmanager", "callee": "useState", "source_file": "C:\\Users\\theco\\Downloads\\edubreezy_web\\edutemp\\src\\components\\teachers\\ShiftManager.jsx", "source_location": "L47"}, {"caller_nid": "shiftmanager_shiftmanager", "callee": "useState", "source_file": "C:\\Users\\theco\\Downloads\\edubreezy_web\\edutemp\\src\\components\\teachers\\ShiftManager.jsx", "source_location": "L48"}, {"caller_nid": "shiftmanager_shiftmanager", "callee": "useMemo", "source_file": "C:\\Users\\theco\\Downloads\\edubreezy_web\\edutemp\\src\\components\\teachers\\ShiftManager.jsx", "source_location": "L51"}, {"caller_nid": "shiftmanager_shiftmanager", "callee": "useEffect", "source_file": "C:\\Users\\theco\\Downloads\\edubreezy_web\\edutemp\\src\\components\\teachers\\ShiftManager.jsx", "source_location": "L53"}, {"caller_nid": "shiftmanager_shiftmanager", "callee": "useEffect", "source_file": "C:\\Users\\theco\\Downloads\\edubreezy_web\\edutemp\\src\\components\\teachers\\ShiftManager.jsx", "source_location": "L59"}, {"caller_nid": "shiftmanager_shiftmanager", "callee": "useMemo", "source_file": "C:\\Users\\theco\\Downloads\\edubreezy_web\\edutemp\\src\\components\\teachers\\ShiftManager.jsx", "source_location": "L117"}, {"caller_nid": "shiftmanager_shiftmanager", "callee": "format", "source_file": "C:\\Users\\theco\\Downloads\\edubreezy_web\\edutemp\\src\\components\\teachers\\ShiftManager.jsx", "source_location": "L224"}, {"caller_nid": "shiftmanager_shiftmanager", "callee": "filter", "source_file": "C:\\Users\\theco\\Downloads\\edubreezy_web\\edutemp\\src\\components\\teachers\\ShiftManager.jsx", "source_location": "L233"}, {"caller_nid": "shiftmanager_shiftmanager", "callee": "filter", "source_file": "C:\\Users\\theco\\Downloads\\edubreezy_web\\edutemp\\src\\components\\teachers\\ShiftManager.jsx", "source_location": "L243"}, {"caller_nid": "shiftmanager_shiftmanager", "callee": "filter", "source_file": "C:\\Users\\theco\\Downloads\\edubreezy_web\\edutemp\\src\\components\\teachers\\ShiftManager.jsx", "source_location": "L253"}, {"caller_nid": "shiftmanager_shiftmanager", "callee": "format", "source_file": "C:\\Users\\theco\\Downloads\\edubreezy_web\\edutemp\\src\\components\\teachers\\ShiftManager.jsx", "source_location": "L314"}, {"caller_nid": "shiftmanager_shiftmanager", "callee": "map", "source_file": "C:\\Users\\theco\\Downloads\\edubreezy_web\\edutemp\\src\\components\\teachers\\ShiftManager.jsx", "source_location": "L333"}, {"caller_nid": "shiftmanager_shiftmanager", "callee": "map", "source_file": "C:\\Users\\theco\\Downloads\\edubreezy_web\\edutemp\\src\\components\\teachers\\ShiftManager.jsx", "source_location": "L456"}, {"caller_nid": "shiftmanager_shiftmanager", "callee": "filter", "source_file": "C:\\Users\\theco\\Downloads\\edubreezy_web\\edutemp\\src\\components\\teachers\\ShiftManager.jsx", "source_location": "L456"}]}